serum/__init__.py
serum/_context.py
serum/_dependency.py
serum/_dependency_configuration.py
serum/_functions.py
serum/_inject.py
serum/_injected_dependency.py
serum/_key.py
serum/exceptions.py
serum-5.1.0.dist-info/METADATA
serum-5.1.0.dist-info/RECORD
serum-5.1.0.dist-info/WHEEL
serum-5.1.0.dist-info/top_level.txt
