Metadata-Version: 2.1
Name: serum
Version: 5.1.0
Summary: Dependency Injection library for Python 3
Home-page: https://github.com/suned/serum
Author: Sune Debel
Author-email: sd@dybro-debel.dk
License: MIT
Keywords: dependency-injection,solid,inversion-of-control
Platform: UNKNOWN
Requires-Python: >=3.6
